humobi/__init__.py
humobi/measures/__init__.py
humobi/measures/collective.py
humobi/measures/individual.py
humobi/misc/__init__.py
humobi/misc/create_grid.py
humobi/misc/generators.py
humobi/misc/utils.py
humobi/models/__init__.py
humobi/models/agent_module/__init__.py
humobi/models/agent_module/agent_class.py
humobi/models/agent_module/generate_agents.py
humobi/models/mobility_model/__init__.py
humobi/models/mobility_model/data_generating.py
humobi/models/mobility_model/data_sampling.py
humobi/models/mobility_model/who.py
humobi/models/spatial_modules/__init__.py
humobi/models/spatial_modules/where.py
humobi/models/spatial_tools/__init__.py
humobi/models/spatial_tools/distributions.py
humobi/models/spatial_tools/filtering.py
humobi/models/spatial_tools/generating.py
humobi/models/spatial_tools/misc.py
humobi/models/temporal_tools/__init__.py
humobi/models/temporal_tools/cluster_traj.py
humobi/models/temporal_tools/when.py
humobi/predictors/__init__.py
humobi/predictors/deep.py
humobi/predictors/markov.py
humobi/predictors/sparse.py
humobi/predictors/wrapper.py
humobi/preprocessing/__init__.py
humobi/preprocessing/filters.py
humobi/preprocessing/spatial_aggregation.py
humobi/preprocessing/temporal_aggregation.py
humobi/structures/__init__.py
humobi/structures/trajectory.py
humobi/tests/__init__.py
humobi/tests/test_structures.py
humobi/tools/__init__.py
humobi/tools/processing.py
humobi/tools/user_statistics.py
HuMobi-0.1.17.dist-info/LICENSE
HuMobi-0.1.17.dist-info/METADATA
HuMobi-0.1.17.dist-info/WHEEL
HuMobi-0.1.17.dist-info/top_level.txt
HuMobi-0.1.17.dist-info/RECORD
