Metadata-Version: 2.1
Name: HuMobi
Version: 0.1.17
Summary: A library dedicated to human mobility data processing
Home-page: https://github.com/SmolakK/HuMobi
Author: Kamil Smolak
Author-email: kamil.smolak@upwr.edu.pl
License: BSD 3-Clause License
Project-URL: Bug Tracker, https://github.com/SmolakK/HuMobi/issues
Classifier: Programming Language :: Python :: 3
Classifier: Operating System :: OS Independent
Requires-Python: >=3.7
License-File: LICENSE
Requires-Dist: pandas >=1.1.5
Requires-Dist: geopandas >=0.8.1
Requires-Dist: tqdm >=4.59.0
Requires-Dist: scipy >=1.5.2
Requires-Dist: numpy >=0.19.5
Requires-Dist: scikit-learn >=0.23.2
Requires-Dist: biopython >=1.78
Requires-Dist: shapely >=1.7.1
Requires-Dist: numba >=0.51.2
Requires-Dist: tensorflow >=2.4.1
Requires-Dist: geofeather >=0.3.0
